tvscreener/__init__.py
tvscreener/beauty.py
tvscreener/exceptions.py
tvscreener/filter.py
tvscreener/py.typed
tvscreener/util.py
tvscreener/core/__init__.py
tvscreener/core/base.py
tvscreener/core/bond.py
tvscreener/core/coin.py
tvscreener/core/crypto.py
tvscreener/core/forex.py
tvscreener/core/futures.py
tvscreener/core/stock.py
tvscreener/field/__init__.py
tvscreener/field/bond.py
tvscreener/field/coin.py
tvscreener/field/crypto.py
tvscreener/field/forex.py
tvscreener/field/futures.py
tvscreener/field/presets.py
tvscreener/field/stock.py
tvscreener/ta/__init__.py
tvscreener-0.1.0.dist-info/licenses/LICENSE
tvscreener-0.1.0.dist-info/METADATA
tvscreener-0.1.0.dist-info/WHEEL
tvscreener-0.1.0.dist-info/top_level.txt
tvscreener-0.1.0.dist-info/RECORD
