Metadata-Version: 2.4
Name: tvscreener
Version: 0.1.0
Summary: TradingView Screener API
Author: DeepEntropy
License-Expression: MIT
Project-URL: Homepage, https://github.com/deepentropy/tvscreener
Project-URL: Repository, https://github.com/deepentropy/tvscreener
Project-URL: Documentation, https://github.com/deepentropy/tvscreener
Project-URL: Bug Tracker, https://github.com/deepentropy/tvscreener/issues
Keywords: finance,tradingview,technical-analysis
Classifier: Development Status :: 4 - Beta
Classifier: Intended Audience :: Developers
Classifier: Intended Audience :: Financial and Insurance Industry
Classifier: Programming Language :: Python :: 3
Classifier: Programming Language :: Python :: 3.10
Classifier: Programming Language :: Python :: 3.11
Classifier: Programming Language :: Python :: 3.12
Classifier: Operating System :: OS Independent
Classifier: Topic :: Office/Business :: Financial
Classifier: Topic :: Software Development :: Libraries :: Python Modules
Requires-Python: >=3.10
License-File: LICENSE
Requires-Dist: pandas>=1.3.0
Requires-Dist: requests>=2.27.1
Provides-Extra: dev
Requires-Dist: pytest>=7.0.0; extra == "dev"
Requires-Dist: pytest-cov>=4.0.0; extra == "dev"
Requires-Dist: build>=1.0.0; extra == "dev"
Requires-Dist: twine>=4.0.0; extra == "dev"
Dynamic: license-file
